displayhatmini/__init__.py
displayhatmini/__main__.py
displayhatmini-0.0.2.dist-info/LICENSE.txt
displayhatmini-0.0.2.dist-info/METADATA
displayhatmini-0.0.2.dist-info/WHEEL
displayhatmini-0.0.2.dist-info/top_level.txt
displayhatmini-0.0.2.dist-info/RECORD
